tulca/__init__.py
tulca/tulca.py
tulca-0.1.0.dist-info/licenses/LICENSE
tulca-0.1.0.dist-info/METADATA
tulca-0.1.0.dist-info/WHEEL
tulca-0.1.0.dist-info/top_level.txt
tulca-0.1.0.dist-info/RECORD
