Metadata-Version: 2.4
Name: tulca
Version: 0.1.0
License-File: LICENSE
Requires-Dist: autograd
Requires-Dist: numpy
Requires-Dist: scipy
Requires-Dist: tensorly
Requires-Dist: pymanopt
Dynamic: license-file
Dynamic: requires-dist
